AIWatchTower/AIWatchTower.py
AIWatchTower/__init__.py
AIWatchTower/__main__.py
AIWatchTower/tests/__init__.py
AIWatchTower-0.0.1.dist-info/LICENSE.txt
AIWatchTower-0.0.1.dist-info/METADATA
AIWatchTower-0.0.1.dist-info/WHEEL
AIWatchTower-0.0.1.dist-info/top_level.txt
AIWatchTower-0.0.1.dist-info/RECORD
